final_assignment_410952/__init__.py
final_assignment_410952/myfunctions.py
final_assignment_410952-0.1.1.dist-info/METADATA
final_assignment_410952-0.1.1.dist-info/WHEEL
final_assignment_410952-0.1.1.dist-info/top_level.txt
final_assignment_410952-0.1.1.dist-info/RECORD
